MANIFEST.in
install_requires.txt
setup.py
custom_terraform/__init__.py
custom_terraform/custom_terraform.py
custom_terraform.egg-info/PKG-INFO
custom_terraform.egg-info/SOURCES.txt
custom_terraform.egg-info/dependency_links.txt
custom_terraform.egg-info/top_level.txt